LocalDataManager/__init__.py
LocalDataManager/file_manager.py
LocalDataManager/db/__init__.py
LocalDataManager/db/db_classes.py
LocalDataManager-0.1.1.dist-info/LICENSE
LocalDataManager-0.1.1.dist-info/METADATA
LocalDataManager-0.1.1.dist-info/WHEEL
LocalDataManager-0.1.1.dist-info/top_level.txt
LocalDataManager-0.1.1.dist-info/RECORD
