Metadata-Version: 2.1
Name: LocalDataManager
Version: 0.1.1
Summary: A package for facilitating local file management
Author-email: Blaine Perry <blainecperry@gmail.com>
Project-URL: Homepage, https://github.com/bcperry/LocalDataManager
Project-URL: Issues, https://github.com/bcperry/LocalDataManager/issues
Classifier: Programming Language :: Python :: 3
Classifier: License :: OSI Approved :: MIT License
Classifier: Operating System :: OS Independent
Requires-Python: >=3.8
License-File: LICENSE
Requires-Dist: pandas
Requires-Dist: sqlalchemy
